earthlib/BRDFCorrect.py
earthlib/BrightMask.py
earthlib/BurnPVSoil.py
earthlib/CloudMask.py
earthlib/NIRv.py
earthlib/Scale.py
earthlib/ShadeMask.py
earthlib/SoilPVNPV.py
earthlib/Unmix.py
earthlib/VegImperviousSoil.py
earthlib/__init__.py
earthlib/config.py
earthlib/data/collections.json
earthlib/data/spectra.csv
earthlib/data/spectra.sli
earthlib/data/spectra.sli.hdr
earthlib/errors.py
earthlib/read.py
earthlib/utils.py
earthlib-0.3.2.dist-info/LICENSE
earthlib-0.3.2.dist-info/METADATA
earthlib-0.3.2.dist-info/WHEEL
earthlib-0.3.2.dist-info/RECORD
