Metadata-Version: 2.1
Name: earthlib
Version: 0.3.2
Summary: A global spectral library with earth engine tools for satellite land cover mapping.
License: MIT
Author: earth-chris
Author-email: cbanders@alumni.stanford.edu
Requires-Python: >=3.9,<4.0
Classifier: License :: OSI Approved :: MIT License
Classifier: Programming Language :: Python :: 3
Classifier: Programming Language :: Python :: 3.9
Classifier: Programming Language :: Python :: 3.10
Classifier: Programming Language :: Python :: 3.11
Requires-Dist: earthengine-api (>=0.1.317)
Requires-Dist: numpy (>=1.21.5)
Requires-Dist: pandas (>=1.3.5)
Requires-Dist: spectral (>=0.22.4)
Requires-Dist: tqdm (>=4.63.0)
